nyvalis/__init__.py
nyvalis/bundler/__init__.py
nyvalis/bundler/utils.py
nyvalis/bundler/windows/__init__.py
nyvalis/bundler/windows/default.wxs
nyvalis/bundler/windows/msi.py
nyvalis/cli/__init__.py
nyvalis/cli/commands/__init__.py
nyvalis/cli/commands/build/__init__.py
nyvalis/cli/commands/models.py
nyvalis/cli/commands/new/__init__.py
nyvalis/cli/commands/new/react/__init__.py
nyvalis/cli/commands/new/react/features.py
nyvalis/cli/commands/new/react/typecheck.py
nyvalis/cli/commands/new/svelte/__init__.py
nyvalis/cli/commands/new/svelte/features.py
nyvalis/cli/commands/new/svelte/typecheck.py
nyvalis/cli/commands/run/__init__.py
nyvalis/cli/commands/utils.py
nyvalis/cli/templates/options/react/base/.gitignore
nyvalis/cli/templates/options/react/base/package.json
nyvalis/cli/templates/options/react/base/public/logo.svg
nyvalis/cli/templates/options/react/base/README.md
nyvalis/cli/templates/options/react/base/src/App.css
nyvalis/cli/templates/options/react/base/src/index.css
nyvalis/cli/templates/options/react/feats/eslint/eslint.config.js
nyvalis/cli/templates/options/react/feats/prettier/.prettierignore
nyvalis/cli/templates/options/react/feats/prettier/.prettierrc
nyvalis/cli/templates/options/react/feats/tailwindcss/App.css
nyvalis/cli/templates/options/react/feats/tailwindcss/App.tsx
nyvalis/cli/templates/options/react/feats/tailwindcss/index.css
nyvalis/cli/templates/options/react/feats/tailwindcss/tailwind.config.js
nyvalis/cli/templates/options/react/feats/tailwindcss/vite.config.js
nyvalis/cli/templates/options/react/typecheck/javascript/App.jsx
nyvalis/cli/templates/options/react/typecheck/javascript/index.html
nyvalis/cli/templates/options/react/typecheck/javascript/main.jsx
nyvalis/cli/templates/options/react/typecheck/javascript/vite.config.js
nyvalis/cli/templates/options/react/typecheck/typescript/App.tsx
nyvalis/cli/templates/options/react/typecheck/typescript/index.html
nyvalis/cli/templates/options/react/typecheck/typescript/main.tsx
nyvalis-0.1.4.dist-info/entry_points.txt
nyvalis-0.1.4.dist-info/METADATA
nyvalis-0.1.4.dist-info/WHEEL
nyvalis-0.1.4.dist-info/RECORD
