Metadata-Version: 2.3
Name: nyvalis
Version: 0.1.4
Summary: Nyvalis is a lightweight Python library for building modern desktop applications using web technologies and webview.
Author: beqm
Author-email: brenomartinsmb@gmail.com
Requires-Python: >=3.12,<3.14
Classifier: Programming Language :: Python :: 3
Classifier: Programming Language :: Python :: 3.12
Classifier: Programming Language :: Python :: 3.13
Requires-Dist: click (>=8.1.8)
Requires-Dist: jinja2 (>=3.1.5,<4.0.0)
Requires-Dist: nuitka (>=2.6.6,<3.0.0)
Requires-Dist: psutil (>=6.1.1,<7.0.0)
Requires-Dist: pythonnet (>=3.0.5)
Requires-Dist: questionary (>=2.1.0,<3.0.0)
Requires-Dist: requests (>=2.32.3,<3.0.0)
